{
  "$schema": "https://static.modelcontextprotocol.io/schemas/2025-12-11/server.schema.json",
  "name": "io.github.skivuha/federal-compass-mcp",
  "title": "Federal Compass MCP",
  "description": "Your AI compass from private sector to federal career — search USAJobs, explain federal concepts, analyze resumes",
  "repository": {
    "url": "https://github.com/skivuha/federal-compass-mcp",
    "source": "github"
  },
  "version": "0.1.5",
  "packages": [
    {
      "registryType": "npm",
      "registryBaseUrl": "https://registry.npmjs.org",
      "identifier": "federal-compass-mcp",
      "version": "0.1.5",
      "transport": {
        "type": "stdio"
      },
      "environmentVariables": [
        {
          "name": "USAJOBS_API_KEY",
          "description": "API key from developer.usajobs.gov",
          "required": true
        },
        {
          "name": "USAJOBS_EMAIL",
          "description": "Email used when requesting the API key",
          "required": true
        }
      ]
    }
  ]
}
